nonebot_plugin_mahjong_utils-0.5.0.dist-info/METADATA
nonebot_plugin_mahjong_utils-0.5.0.dist-info/WHEEL
nonebot_plugin_mahjong_utils-0.5.0.dist-info/entry_points.txt
nonebot_plugin_mahjong_utils-0.5.0.dist-info/licenses/LICENSE
nonebot_plugin_mahjong_utils/__init__.py
nonebot_plugin_mahjong_utils/ac.py
nonebot_plugin_mahjong_utils/config.py
nonebot_plugin_mahjong_utils/mapper/__init__.py
nonebot_plugin_mahjong_utils/mapper/htmlrender/__init__.py
nonebot_plugin_mahjong_utils/mapper/htmlrender/templates/__init__.py
nonebot_plugin_mahjong_utils/mapper/htmlrender/templates/hora.html
nonebot_plugin_mahjong_utils/mapper/htmlrender/templates/macro.html
nonebot_plugin_mahjong_utils/mapper/htmlrender/templates/shanten_with_furo_chance.html
nonebot_plugin_mahjong_utils/mapper/htmlrender/templates/shanten_with_got.html
nonebot_plugin_mahjong_utils/mapper/htmlrender/templates/shanten_without_got.html
nonebot_plugin_mahjong_utils/mapper/htmlrender/templates/style.css
nonebot_plugin_mahjong_utils/mapper/htmlrender/templates/tiles/1m.png
nonebot_plugin_mahjong_utils/mapper/htmlrender/templates/tiles/1p.png
nonebot_plugin_mahjong_utils/mapper/htmlrender/templates/tiles/1s.png
nonebot_plugin_mahjong_utils/mapper/htmlrender/templates/tiles/1z.png
nonebot_plugin_mahjong_utils/mapper/htmlrender/templates/tiles/2m.png
nonebot_plugin_mahjong_utils/mapper/htmlrender/templates/tiles/2p.png
nonebot_plugin_mahjong_utils/mapper/htmlrender/templates/tiles/2s.png
nonebot_plugin_mahjong_utils/mapper/htmlrender/templates/tiles/2z.png
nonebot_plugin_mahjong_utils/mapper/htmlrender/templates/tiles/3m.png
nonebot_plugin_mahjong_utils/mapper/htmlrender/templates/tiles/3p.png
nonebot_plugin_mahjong_utils/mapper/htmlrender/templates/tiles/3s.png
nonebot_plugin_mahjong_utils/mapper/htmlrender/templates/tiles/3z.png
nonebot_plugin_mahjong_utils/mapper/htmlrender/templates/tiles/4m.png
nonebot_plugin_mahjong_utils/mapper/htmlrender/templates/tiles/4p.png
nonebot_plugin_mahjong_utils/mapper/htmlrender/templates/tiles/4s.png
nonebot_plugin_mahjong_utils/mapper/htmlrender/templates/tiles/4z.png
nonebot_plugin_mahjong_utils/mapper/htmlrender/templates/tiles/5m.png
nonebot_plugin_mahjong_utils-0.5.0.dist-info/RECORD
