Metadata-Version: 2.1
Name: nonebot-plugin-mahjong-utils
Version: 0.5.0
Author-Email: ssttkkl <huang.wen.long@hotmail.com>
License: MIT
Project-URL: repository, https://github.com/ssttkkl/nonebot-plugin-mahjong-utils
Requires-Python: <3.13,>=3.10
Requires-Dist: nonebot2<3.0.0,>=2.0.0
Requires-Dist: mahjong-utils<1.0.0,>=0.7.4
Requires-Dist: nonebot-plugin-htmlrender<1.0.0.0,>=0.2.0.3
Requires-Dist: nonebot-plugin-send-anything-anywhere>=0.3.0
Requires-Dist: ssttkkl-nonebot-utils<1.0.0,>=0.1.22
Requires-Dist: nonebot-plugin-alconna>=0.57.2
Requires-Dist: nonebot-plugin-access-control-api>=1.2.1
Provides-Extra: detect
Requires-Dist: mahjong-detector>=0.0.6; extra == "detect"
